README.md
setup.py
bin/nuphy2
bin/sriminst.sh
nuphy2/__init__.py
nuphy2/compounds.py
nuphy2/config.py
nuphy2/decay.py
nuphy2/dechain.py
nuphy2/h5.py
nuphy2/isotope.py
nuphy2/kinematics.py
nuphy2/prj_utils.py
nuphy2/pubq_fig.py
nuphy2/radcap.py
nuphy2/react.py
nuphy2/rolfs.py
nuphy2/schemes.py
nuphy2/srim.py
nuphy2/tendl.py
nuphy2/version.py
nuphy2/xsections.py
nuphy2/yields.py
nuphy2.egg-info/PKG-INFO
nuphy2.egg-info/SOURCES.txt
nuphy2.egg-info/dependency_links.txt
nuphy2.egg-info/requires.txt
nuphy2.egg-info/top_level.txt
nuphy2/data/#exploring_kinematics.cpp#
nuphy2/data/All-nuclides_lara.zip
nuphy2/data/ame2020.txt
nuphy2/data/decay_lara.parquet
nuphy2/data/decay_to_parquet.py
nuphy2/data/exploring_kinematics.cpp
nuphy2/data/libs2013.tgz
nuphy2/data/mass_1.mas20.txt
nuphy2/data/nubase.mas12
nuphy2/data/nubase2016.txt
nuphy2/data/decay/41021808.pdf
nuphy2/data/decay/Ac-225.lara.txt
nuphy2/data/decay/Ac-227.lara.txt
nuphy2/data/decay/Ac-228.lara.txt
nuphy2/data/decay/Ag-108.lara.txt
nuphy2/data/decay/Ag-108m.lara.txt
nuphy2/data/decay/Ag-110.lara.txt
nuphy2/data/decay/Ag-110m.lara.txt
nuphy2/data/decay/Al-26.lara.txt
nuphy2/data/decay/Am-241.lara.txt
nuphy2/data/decay/Am-242.lara.txt
nuphy2/data/decay/Am-242m.lara.txt
nuphy2/data/decay/Am-243.lara.txt
nuphy2/data/decay/Am-244.lara.txt
nuphy2/data/decay/Am-244m.lara.txt
nuphy2/data/decay/Ar-37.lara.txt
nuphy2/data/decay/Ar-41.lara.txt
nuphy2/data/decay/At-211.lara.txt
nuphy2/data/decay/At-215.lara.txt
nuphy2/data/decay/At-217.lara.txt
nuphy2/data/decay/At-218.lara.txt
nuphy2/data/decay/At-219.lara.txt
nuphy2/data/decay/Au-195.lara.txt
nuphy2/data/decay/Au-198.lara.txt
nuphy2/data/decay/Ba-133.lara.txt
nuphy2/data/decay/Ba-137m.lara.txt
nuphy2/data/decay/Ba-140.lara.txt
nuphy2/data/decay/Be-7.lara.txt
nuphy2/data/decay/Bi-207.lara.txt
nuphy2/data/decay/Bi-210.lara.txt
nuphy2/data/decay/Bi-211.lara.txt
nuphy2/data/decay/Bi-212.lara.txt
nuphy2/data/decay/Bi-213.lara.txt
nuphy2/data/decay/Bi-214.lara.txt
nuphy2/data/decay/Bi-215.lara.txt
nuphy2/data/decay/Br-76.lara.txt
nuphy2/data/decay/C-11.lara.txt
nuphy2/data/decay/C-14.lara.txt
nuphy2/data/decay/Ca-41.lara.txt
