Metadata-Version: 2.1
Name: nuphy2
Version: 0.8.9
Summary: NUclear PHYsics python package - try #2
Home-page: http://gitlab.com/jaromrax/nuphy2
Author: JM
Author-email: jaromrax@gmail.com
License: GPL2
